[
  {
    "ID": "fiery_quest",
    "PROPER_NAME": "Fiery Quest",
    "NAMES": [
      "fiery_quest"
    ],
    "DESCRIPTION": "Upon drawing 20 total #yStatus cards, gain the #yFire #yBreathing+ #ybuff instead."
  },

  {
    "ID": "illusionary_quest",
    "PROPER_NAME": "Illusionary Quest",
    "NAMES": [
      "illusionary_quest"
    ],
    "DESCRIPTION": "Every 3rd time you play #yIllusion #yNeutralize, Draw #b3 cards."
  },

  {
    "ID": "slow",
    "PROPER_NAME": "Slow",
    "NAMES": [
      "slow"
    ],
    "DESCRIPTION": "Whenever you play a card, #ythe #yEnemy receives #b10% more damage from #yAttacks this turn."
  },

  {
    "ID": "crystallize",
    "PROPER_NAME": "Crystallize",
    "NAMES": [
      "crystallize"
    ],
    "DESCRIPTION": "At the end of your turn, gain an Orb slot, #yChannel a random Orb, and gain #b1 #yDexterity."
  }
]